[
  {
    "value": "labour along缓慢而费力地前进",
    "prefix": "l"
  },
  {
    "value": "laugh at因…而发笑/嘲笑",
    "prefix": "l"
  },
  {
    "value": "laugh off用笑摆脱(困境等)",
    "prefix": "l"
  },
  {
    "value": "laugh over笑着谈论",
    "prefix": "l"
  },
  {
    "value": "launch out(船)下水/开始新事情",
    "prefix": "l"
  },
  {
    "value": "lay aside把…放在一边/储存",
    "prefix": "l"
  },
  {
    "value": "lay down放下/铺设(铁路)",
    "prefix": "l"
  },
  {
    "value": "lay hold of握住/控制住/占有",
    "prefix": "l"
  },
  {
    "value": "lay off停止/(临时)解雇",
    "prefix": "l"
  },
  {
    "value": "lay out花费/布置/摆开",
    "prefix": "l"
  },
  {
    "value": "lay over涂/覆盖/压倒",
    "prefix": "l"
  },
  {
    "value": "lay up贮存/储蓄/暂停使用",
    "prefix": "l"
  },
  {
    "value": "lead the way引路/带路/示范",
    "prefix": "l"
  },
  {
    "value": "lead to通向/导致/引起",
    "prefix": "l"
  },
  {
    "value": "lead up to把…一直带领到/导致",
    "prefix": "l"
  },
  {
    "value": "learn by heart记住/背诵",
    "prefix": "l"
  },
  {
    "value": "learn from学习/向…学习",
    "prefix": "l"
  },
  {
    "value": "learn of听到/获悉…的事",
    "prefix": "l"
  },
  {
    "value": "learn off记熟/背下来",
    "prefix": "l"
  },
  {
    "value": "leave alone听其自然/不要去管",
    "prefix": "l"
  },
  {
    "value": "leave behind丢弃/留下/忘记携带",
    "prefix": "l"
  },
  {
    "value": "leave off(使)停止/停下来",
    "prefix": "l"
  },
  {
    "value": "leave out忽略/遗漏/省略",
    "prefix": "l"
  },
  {
    "value": "let alone不干涉/不碰",
    "prefix": "l"
  },
  {
    "value": "let down放下/降低/使…失望",
    "prefix": "l"
  },
  {
    "value": "let go放开/释放/发射",
    "prefix": "l"
  },
  {
    "value": "let in让…进入/放…出来",
    "prefix": "l"
  },
  {
    "value": "let off放(炮)/开(枪)/宽恕",
    "prefix": "l"
  },
  {
    "value": "let out放掉(水等)/发出",
    "prefix": "l"
  },
  {
    "value": "let up减小/(雨等)渐渐停止",
    "prefix": "l"
  },
  {
    "value": "lie down躺下/(故意)躺下不干",
    "prefix": "l"
  },
  {
    "value": "lie in在于/分娩/睡懒觉",
    "prefix": "l"
  },
  {
    "value": "lie on依赖/压迫/折磨(人)",
    "prefix": "l"
  },
  {
    "value": "lie over等待以后处理",
    "prefix": "l"
  },
  {
    "value": "lie up卧床/(船)入坞",
    "prefix": "l"
  },
  {
    "value": "light up照亮/点(烟)",
    "prefix": "l"
  },
  {
    "value": "like any thing象什么似地/拼命地",
    "prefix": "l"
  },
  {
    "value": "limber up使柔软/柔和一下身体",
    "prefix": "l"
  },
  {
    "value": "line up排队/使排成一行",
    "prefix": "l"
  },
  {
    "value": "link up把…连(衔)接起来",
    "prefix": "l"
  },
  {
    "value": "listen for等着听…(的声音)",
    "prefix": "l"
  },
  {
    "value": "listen into收听/监听/偷听",
    "prefix": "l"
  },
  {
    "value": "listen to听/倾听",
    "prefix": "l"
  },
  {
    "value": "little by little一点一点地/逐渐地",
    "prefix": "l"
  },
  {
    "value": "live off住在…之外/靠…生活",
    "prefix": "l"
  },
  {
    "value": "live on靠…生活/以…为食",
    "prefix": "l"
  },
  {
    "value": "live out活过(某一段时间)",
    "prefix": "l"
  },
  {
    "value": "live through经历过/度过/经受住",
    "prefix": "l"
  },
  {
    "value": "live up to无愧于/做到/符合",
    "prefix": "l"
  },
  {
    "value": "live with接受/忍受/承认",
    "prefix": "l"
  },
  {
    "value": "lock oneself in把自己关在里面",
    "prefix": "l"
  },
  {
    "value": "lock out把…关在外面",
    "prefix": "l"
  },
  {
    "value": "long before在…以前很久",
    "prefix": "l"
  },
  {
    "value": "long for渴望",
    "prefix": "l"
  },
  {
    "value": "long since很久以前/很久以来",
    "prefix": "l"
  },
  {
    "value": "look after照顾/目送/负责处理",
    "prefix": "l"
  },
  {
    "value": "look at看着/注视/察看",
    "prefix": "l"
  },
  {
    "value": "look back回顾/回想/停止不前",
    "prefix": "l"
  },
  {
    "value": "look black怒视",
    "prefix": "l"
  },
  {
    "value": "look down on蔑视/看不起",
    "prefix": "l"
  },
  {
    "value": "look for寻找/寻求/指望",
    "prefix": "l"
  },
  {
    "value": "look forward to盼望/期待/预期",
    "prefix": "l"
  },
  {
    "value": "look in顺便看望/顺便访问",
    "prefix": "l"
  },
  {
    "value": "look into观察/调查/窥视",
    "prefix": "l"
  },
  {
    "value": "look on旁观/观看/面向",
    "prefix": "l"
  },
  {
    "value": "look out留神/朝外看/照料",
    "prefix": "l"
  },
  {
    "value": "look over从…上面看过去/检查",
    "prefix": "l"
  },
  {
    "value": "look round掉头看/观光/察看",
    "prefix": "l"
  },
  {
    "value": "look through(从头至尾)浏览/温习",
    "prefix": "l"
  },
  {
    "value": "look to照管/留心/指望",
    "prefix": "l"
  },
  {
    "value": "look up向上看/查出",
    "prefix": "l"
  },
  {
    "value": "look up to sb.尊敬/敬仰",
    "prefix": "l"
  },
  {
    "value": "lose heart灰心/泄气",
    "prefix": "l"
  },
  {
    "value": "lose no time立即",
    "prefix": "l"
  },
  {
    "value": "lose one's hair脱发/发脾气",
    "prefix": "l"
  },
  {
    "value": "lose one's head慌乱/被砍头",
    "prefix": "l"
  },
  {
    "value": "lose one's heart to心被…俘去/爱上",
    "prefix": "l"
  },
  {
    "value": "lose one's nerves变得慌张/不知所措",
    "prefix": "l"
  },
  {
    "value": "lose one's temper发怒/发脾气",
    "prefix": "l"
  },
  {
    "value": "lose sight of看不见",
    "prefix": "l"
  },
  {
    "value": "lost one's balance失去平衡/心慌意乱",
    "prefix": "l"
  },
  {
    "value": "lots and lots许许多多(的)",
    "prefix": "l"
  },
  {
    "value": "lots of大量/许多",
    "prefix": "l"
  }
]